podcastfy/__init__.py
podcastfy/api/fast_app.py
podcastfy/client.py
podcastfy/config.yaml
podcastfy/content_generator.py
podcastfy/content_parser/__init__.py
podcastfy/content_parser/content_extractor.py
podcastfy/content_parser/pdf_extractor.py
podcastfy/content_parser/website_extractor.py
podcastfy/content_parser/youtube_transcriber.py
podcastfy/conversation_config.yaml
podcastfy/data/audio/tmp/tmpibdcmvin/1_answer.mp3
podcastfy/data/audio/tmp/tmpibdcmvin/1_question.mp3
podcastfy/data/audio/tmp/tmpibdcmvin/2_answer.mp3
podcastfy/data/audio/tmp/tmpibdcmvin/2_question.mp3
podcastfy/data/audio/tmp/tmpibdcmvin/3_answer.mp3
podcastfy/data/audio/tmp/tmpibdcmvin/3_question.mp3
podcastfy/data/audio/tmp/tmpibdcmvin/4_answer.mp3
podcastfy/data/audio/tmp/tmpibdcmvin/4_question.mp3
podcastfy/data/audio/tmp/tmpibdcmvin/5_answer.mp3
podcastfy/data/audio/tmp/tmpibdcmvin/5_question.mp3
podcastfy/data/audio/tmp/tmpibdcmvin/6_answer.mp3
podcastfy/data/audio/tmp/tmpibdcmvin/6_question.mp3
podcastfy/text_to_speech.py
podcastfy/tts/base.py
podcastfy/tts/factory.py
podcastfy/tts/providers/edge.py
podcastfy/tts/providers/elevenlabs.py
podcastfy/tts/providers/gemini.py
podcastfy/tts/providers/geminimulti.py
podcastfy/tts/providers/openai.py
podcastfy/utils/config.py
podcastfy/utils/config_conversation.py
podcastfy/utils/logger.py
podcastfy-0.4.3.dist-info/METADATA
podcastfy-0.4.3.dist-info/WHEEL
podcastfy-0.4.3.dist-info/entry_points.txt
podcastfy-0.4.3.dist-info/licenses/LICENSE
podcastfy-0.4.3.dist-info/licenses/NOTICE
podcastfy-0.4.3.dist-info/RECORD
