Metadata-Version: 2.4
Name: podcastfy
Version: 0.4.3
Summary: An Open Source alternative to NotebookLM's podcast feature: Transforming Multimodal Content into Captivating Multilingual Audio Conversations with GenAI
License: Apache-2.0
License-File: LICENSE
License-File: NOTICE
Author: Tharsis T. P. Souza
Requires-Python: >=3.11,<4.0
Classifier: License :: OSI Approved :: Apache Software License
Classifier: Programming Language :: Python :: 3
Classifier: Programming Language :: Python :: 3.11
Classifier: Programming Language :: Python :: 3.12
Classifier: Programming Language :: Python :: 3.13
Classifier: Programming Language :: Python :: 3.14
Requires-Dist: PyMuPDF (>=1.24.11,<2.0.0)
Requires-Dist: beautifulsoup4 (>=4.12.3,<5.0.0)
Requires-Dist: cython (>=3.0.11,<4.0.0)
Requires-Dist: edge-tts (>=7.2.3,<8.0.0)
Requires-Dist: elevenlabs (>=1.9.0,<2.0.0)
Requires-Dist: ffmpeg (>=1.4,<2.0)
Requires-Dist: fuzzywuzzy (>=0.18.0,<0.19.0)
Requires-Dist: google-cloud-texttospeech (>=2.21.0,<3.0.0)
Requires-Dist: google-genai (>=1.46.0,<2.0.0)
Requires-Dist: google-generativeai (>=0.8.2,<0.9.0)
Requires-Dist: httpx (>=0.28.1,<0.29.0)
Requires-Dist: langchain (>=0.3.3,<0.4.0)
Requires-Dist: langchain-community (>=0.3.5,<0.4.0)
Requires-Dist: langchain-google-genai (>=2.0.1,<3.0.0)
Requires-Dist: langchain-google-vertexai (>=2.0.4,<3.0.0)
Requires-Dist: litellm (>=1.52.0,<2.0.0)
Requires-Dist: nbsphinx (>=0.9.5,<0.10.0)
Requires-Dist: nest-asyncio (>=1.6.0,<2.0.0)
Requires-Dist: numpy (>=1,<2)
Requires-Dist: openai (>=1.56.1,<2.0.0)
Requires-Dist: pandas (>=2.2.3,<3.0.0)
Requires-Dist: pandoc (>=2.4,<3.0)
Requires-Dist: pydub (>=0.25.1,<0.26.0)
Requires-Dist: pytest (>=8.3.3,<9.0.0)
Requires-Dist: pytest-xdist (>=3.6.1,<4.0.0)
Requires-Dist: python-dotenv (>=1.0.1,<2.0.0)
Requires-Dist: python-levenshtein (>=0.26.0,<0.27.0)
Requires-Dist: pyyaml (>=6.0.2,<7.0.0)
Requires-Dist: requests (>=2.32.3,<3.0.0)
Requires-Dist: setuptools (>=75.1.0,<76.0.0)
Requires-Dist: sphinx-autodoc-typehints (>=2.5.0,<3.0.0)
Requires-Dist: sphinx-rtd-theme (>=3.0.1,<4.0.0)
Requires-Dist: typer (>=0.12.5,<0.13.0)
Requires-Dist: types-pyyaml (>=6.0.12.20240917,<7.0.0.0)
Requires-Dist: wheel (>=0.44.0,<0.45.0)
Requires-Dist: youtube-transcript-api (>=0.6.2,<0.7.0)
